vardescribe/__init__.py
vardescribe/core.py
vardescribe-0.1.5.dist-info/licenses/LICENSE
vardescribe-0.1.5.dist-info/METADATA
vardescribe-0.1.5.dist-info/WHEEL
vardescribe-0.1.5.dist-info/top_level.txt
vardescribe-0.1.5.dist-info/RECORD
