Metadata-Version: 2.4
Name: vardescribe
Version: 0.1.5
Summary: A simple Python utility to describe the structure, type, and stats of a variable - for sharing with LLMs and other people.
Author-email: Igor Reidler <igormail@gmail.com>
License: MIT License
Project-URL: Homepage, https://github.com/IgorReidler/vardescribe
Project-URL: Issues, https://github.com/IgorReidler/vardescribe/issues
Classifier: Programming Language :: Python :: 3
Classifier: License :: OSI Approved :: MIT License
Classifier: Operating System :: OS Independent
Requires-Python: >=3.6
License-File: LICENSE
Requires-Dist: numpy
Dynamic: license-file
